<?xml version="1.0" encoding="utf-8"?>
<Entity parent="units/rome_infantry_spearman_e">
  <Cost>
    <BuildTime>8</BuildTime>
    <Resources>
      <food>0</food>
      <wood>0</wood>
      <stone>0</stone>
      <metal>70</metal>
    </Resources>
  </Cost> 
  <Identity>
	<VisibleClasses datatype="tokens">Mercenary</VisibleClasses>	
    <Icon>units/celt_infantry_spearman.png</Icon>	
    <SpecificName>Auxiliary Spearman</SpecificName>		
  </Identity>
  <Promotion disable=""/>
  <VisualActor>
    <Actor>units/romans/infantry_spearman_u.xml</Actor>
  </VisualActor>
</Entity>
