<?xml version="1.0" encoding="utf-8"?>
<Entity parent="template_unit_champion_infantry_spearman">
  <Armour>
    <Hack>7</Hack>
    <Pierce>7</Pierce>
    <Crush>7</Crush>
  </Armour>
  <Attack>
    <Melee>
      <Hack>8</Hack>
      <Pierce>16</Pierce>
      <Crush>0.0</Crush>
      <MaxRange>6.0</MaxRange>
      <RepeatTime>1000</RepeatTime>
    </Melee>
    <Charge>
      <Hack>16</Hack>
      <Pierce>32</Pierce>
      <Crush>0.0</Crush>
      <MaxRange>6.0</MaxRange>
      <MinRange>0.0</MinRange>
    </Charge>
  </Attack>
  <Cost>
    <BuildTime>25</BuildTime>
    <Population>2</Population>	
    <Resources>
      <food>100</food>
      <wood>0</wood>
      <stone>0</stone>
      <metal>80</metal>
    </Resources>
  </Cost>
  <Health>
    <Max>250</Max>
  </Health>  
  <Identity>
    <Civ>spart</Civ>
	<GenericName>Spartan Royal Guard</GenericName>
    <SpecificName>Spartiā́tes Hippeis</SpecificName>
    <Tooltip>Powerful infantry with better all around attributes than other spearmen.</Tooltip>
    <History>300 chosen spartans formed the royal guard and were give the title of hippeis (cavalrymen) even though they fought as hoplites.</History>
    <Icon>units/spart_champion_infantry_spear.png</Icon>
  </Identity>
  <VisualActor>
    <Actor>units/spartans/champion_infantry.xml</Actor>
  </VisualActor>
</Entity>
