<?xml version="1.0" encoding="utf-8"?>
<Entity parent="template_unit_cavalry_ranged">
  <Armour>
    <Hack>0</Hack>
    <Pierce>0</Pierce>
    <Crush>0</Crush>
  </Armour>
  <Attack>
    <Ranged>
      <Hack>0</Hack>
      <Pierce>12</Pierce>
      <Crush>0</Crush>
      <MaxRange>28</MaxRange>
      <MinRange>0.0</MinRange>	 	  
      <ProjectileSpeed>75.0</ProjectileSpeed>
      <PrepareTime>2000</PrepareTime>
      <RepeatTime>2000</RepeatTime>
      <PreferredClasses datatype="tokens">Organic</PreferredClasses>	  
      <Spread>1.2</Spread>	 
	  <Bonuses>
		<AntiRangedInfantry>
		  <Classes>Ranged Infantry</Classes>
		  <Multiplier>1.5</Multiplier>
		</AntiRangedInfantry>
		<AntiRangedCavalry>
		  <Classes>Ranged Cavalry</Classes>
		  <Multiplier>1.5</Multiplier>
		</AntiRangedCavalry>		
	  </Bonuses>   	  
    </Ranged>
  </Attack>
  <Cost>
    <Population>4</Population>
    <BuildTime>24</BuildTime>  
    <Resources>
      <food>60</food>
      <wood>40</wood>
	  <metal>0</metal>
      <stone>0</stone>	  
    </Resources>
  </Cost>
  <Health>
    <Max>105</Max>
  </Health>
  <Vision>
    <Range>45</Range>
  </Vision> 
  <Loot>
    <food>6</food>
    <wood>4</wood>
    <stone>0</stone>
    <metal>0</metal>
  </Loot>  
  <UnitMotion>
    <WalkSpeed>12</WalkSpeed>	
  </UnitMotion>     
  <Identity>
    <VisibleClasses datatype="tokens">Javelin AntiRanged1.5</VisibleClasses>
    <GenericName>Cavalry Skirmisher</GenericName>
    <Tooltip>Ranged cavalry. Good against ranged units.</Tooltip>	
  </Identity>
</Entity>
