{
	"genericName": "Soliferrum",
	"description": ".",
	"requirements": {"civ": "iber"},
	"cost": {"food": 0, "wood": 150, "stone": 0, "metal": 450},
	"requirements": {"all": [{"tech": "phase_city"},{"civ": "iber"}]},
	"requirementsTooltip": "Unlocked in City Phase.",
	"icon": "javelin_thong.png",
	"researchTime": 40,
	"tooltip": "Javelin units +25% attack but -10% movement speed.",	
	"modifications": [
		{"value": "Attack/Ranged/Pierce", "multiply": 1.25},
		{"value": "Attack/Melee/Crush", "multiply": 1.25},
	    {"value": "UnitMotion/WalkSpeed", "multiply": 0.9},
	    {"value": "UnitMotion/Run/Speed", "multiply": 0.9}		
	],
	"affects": ["Javelin"]
}