{
	"genericName": "Cleomenian Reforms",
	"description": "Cleomenes III formed pike phalanxes in an attempt to restore Spartan military power.",
	"cost": { "food": 0, "wood": 0, "stone": 0, "metal": 0 },
	"requirements": {"tech": "phase_imperial"},
	"requirementsTooltip": "Unlocked in Imperial Phase.",
	"icon": "helmet_corinthian_crest.png",
	"researchTime": 120,
	"tooltip": "Lacedemonian Phalangites unlocked. Mercenaries -20% metal cost.",
    "modifications": [
	    {"value": "Cost/Resources/metal", "multiply": 0.80}
	],	
	"affects": ["Mercenary"],	
	"soundComplete": "interface/alarm/alarm_upgradearmory.xml"
}
